[
{"autor": "Alessandra Ambrosio",
"avatar": "http://zntent.com/wp-content/uploads/2015/11/Alessandra-Ambrosio-Pictures-1600-x-1200.jpg",
"titulo": "Victoria Secret",
"contenido": "Hoy tengo el desfile",
"fecha": "27/04/2016"},

{"autor": "Miranda Kerr",
"avatar": "http://www.fashiongonerogue.com/wp-content/uploads/2015/07/Miranda-Kerr-Swarovski-2015.jpg",
"titulo": "Victoria Secret",
"contenido": "¿A qué hora lo tienes?",
"fecha": "27/04/2016"},

{"autor": "Pilar Rubio",
"avatar": "https://pbs.twimg.com/profile_images/719850637551366144/21EqZvjl.jpg",
"titulo": "Hormiguero",
"contenido": "Yo hoy salgo con Pablo Motos en el Hormiguero.",
"fecha": "27/04/2016"}

]
